pynput-stubs/METADATA.toml
pynput-stubs/__init__.pyi
pynput-stubs/_info.pyi
pynput-stubs/_util.pyi
pynput-stubs/py.typed
pynput-stubs/keyboard/__init__.pyi
pynput-stubs/keyboard/_base.pyi
pynput-stubs/keyboard/_dummy.pyi
pynput-stubs/mouse/__init__.pyi
pynput-stubs/mouse/_base.pyi
pynput-stubs/mouse/_dummy.pyi
types_pynput-1.8.1.20250801.dist-info/licenses/LICENSE
types_pynput-1.8.1.20250801.dist-info/METADATA
types_pynput-1.8.1.20250801.dist-info/WHEEL
types_pynput-1.8.1.20250801.dist-info/top_level.txt
types_pynput-1.8.1.20250801.dist-info/RECORD
